odoo/addons/muk_web_theme/LICENSE
odoo/addons/muk_web_theme/README.rst
odoo/addons/muk_web_theme/__init__.py
odoo/addons/muk_web_theme/__manifest__.py
odoo/addons/muk_web_theme/data/res_company.xml
odoo/addons/muk_web_theme/doc/changelog.rst
odoo/addons/muk_web_theme/doc/index.rst
odoo/addons/muk_web_theme/models/__init__.py
odoo/addons/muk_web_theme/models/ir_http.py
odoo/addons/muk_web_theme/models/res_company.py
odoo/addons/muk_web_theme/models/res_config_settings.py
odoo/addons/muk_web_theme/models/res_users.py
odoo/addons/muk_web_theme/models/scss_editor.py
odoo/addons/muk_web_theme/static/description/banner.png
odoo/addons/muk_web_theme/static/description/branding_mail_banner.png
odoo/addons/muk_web_theme/static/description/branding_saas_banner.png
odoo/addons/muk_web_theme/static/description/branding_website_banner.png
odoo/addons/muk_web_theme/static/description/icon.png
odoo/addons/muk_web_theme/static/description/icon.svg
odoo/addons/muk_web_theme/static/description/index.html
odoo/addons/muk_web_theme/static/description/logo.png
odoo/addons/muk_web_theme/static/description/preview.png
odoo/addons/muk_web_theme/static/description/screenshot.png
odoo/addons/muk_web_theme/static/description/screenshot_apps.png
odoo/addons/muk_web_theme/static/description/screenshot_chatter.png
odoo/addons/muk_web_theme/static/description/screenshot_customize.png
odoo/addons/muk_web_theme/static/description/screenshot_mobile_apps.png
odoo/addons/muk_web_theme/static/description/screenshot_mobile_form.png
odoo/addons/muk_web_theme/static/description/screenshot_mobile_kanban.png
odoo/addons/muk_web_theme/static/description/screenshot_mobile_menu.png
odoo/addons/muk_web_theme/static/description/screenshot_settings.png
odoo/addons/muk_web_theme/static/description/service_customization.png
odoo/addons/muk_web_theme/static/description/service_development.png
odoo/addons/muk_web_theme/static/description/service_implementation.png
odoo14_addon_muk_web_theme-14.0.1.0.3.dist-info/METADATA
odoo14_addon_muk_web_theme-14.0.1.0.3.dist-info/WHEEL
odoo14_addon_muk_web_theme-14.0.1.0.3.dist-info/top_level.txt
odoo14_addon_muk_web_theme-14.0.1.0.3.dist-info/RECORD
