Metadata-Version: 2.1
Name: odoo14-addon-muk-web-theme
Version: 14.0.1.0.3
Summary: Odoo Community Backend Theme
Home-page: http://www.mukit.at
Author: MuK IT
License: LGPL-3
Platform: UNKNOWN
Classifier: Programming Language :: Python
Classifier: Framework :: Odoo
Classifier: License :: OSI Approved :: GNU Lesser General Public License v3 (LGPLv3)
Requires-Python: >=3.6
Requires-Dist: odoo (<14.1dev,>=14.0a)
